zhenxun_utils/_build_image.py
zhenxun_utils/_build_mat.py
zhenxun_utils/_image_template.py
zhenxun_utils/common_utils.py
zhenxun_utils/enum.py
zhenxun_utils/exception.py
zhenxun_utils/font/HYWenHei-85W.ttf
zhenxun_utils/github_utils/__init__.py
zhenxun_utils/github_utils/const.py
zhenxun_utils/github_utils/func.py
zhenxun_utils/github_utils/models.py
zhenxun_utils/http_utils.py
zhenxun_utils/image_utils.py
zhenxun_utils/log.py
zhenxun_utils/message.py
zhenxun_utils/platform.py
zhenxun_utils/user_agent.py
zhenxun_utils/utils.py
zhenxun_utils-0.2.2.dist-info/LICENSE
zhenxun_utils-0.2.2.dist-info/METADATA
zhenxun_utils-0.2.2.dist-info/WHEEL
zhenxun_utils-0.2.2.dist-info/RECORD
