Metadata-Version: 2.1
Name: zhenxun-utils
Version: 0.2.2
Summary: 小真寻bot的工具类
Author: HibiKier
Author-email: 775757368@qq.com
Requires-Python: >=3.10,<4.0
Classifier: Programming Language :: Python :: 3
Classifier: Programming Language :: Python :: 3.10
Classifier: Programming Language :: Python :: 3.11
Classifier: Programming Language :: Python :: 3.12
Requires-Dist: aiocache (>=0.12.3,<0.13.0)
Requires-Dist: aiofiles (>=24.1.0,<25.0.0)
Requires-Dist: httpx (>=0.27.2,<0.28.0)
Requires-Dist: nonebot-plugin-alconna (>=0.54,<0.55)
Requires-Dist: nonebot-plugin-session (>=0.3.2,<0.4.0)
Requires-Dist: nonebot-plugin-uninfo (>=0.6.0,<0.7.0)
Requires-Dist: pillow (>=10.0.0,<11.0.0)
Requires-Dist: pypinyin (>=0.53.0,<0.54.0)
Requires-Dist: retrying (>=1.3.4,<2.0.0)
Requires-Dist: rich (>=13.9.4,<14.0.0)
Requires-Dist: strenum (>=0.4.15,<0.5.0)
